{
  "timestamp": 1758357137,
  "operations": [
    {
      "src": "C:\\Users\\User pc\\Pictures\\Images\\1676376883611.jpg",
      "dst": "C:\\Users\\User pc\\Pictures\\Images\\Images\\1676376883611.jpg"
    },
    {
      "src": "C:\\Users\\User pc\\Pictures\\Images\\1676376885942.jpg",
      "dst": "C:\\Users\\User pc\\Pictures\\Images\\Images\\1676376885942.jpg"
    },
    {
      "src": "C:\\Users\\User pc\\Pictures\\Images\\1676376886774.jpg",
      "dst": "C:\\Users\\User pc\\Pictures\\Images\\Images\\1676376886774.jpg"
    },
    {
      "src": "C:\\Users\\User pc\\Pictures\\Images\\1676376887614.jpg",
      "dst": "C:\\Users\\User pc\\Pictures\\Images\\Images\\1676376887614.jpg"
    },
    {
      "src": "C:\\Users\\User pc\\Pictures\\Images\\1676376888381.jpg",
      "dst": "C:\\Users\\User pc\\Pictures\\Images\\Images\\1676376888381.jpg"
    },
    {
      "src": "C:\\Users\\User pc\\Pictures\\Images\\1676376889173.jpg",
      "dst": "C:\\Users\\User pc\\Pictures\\Images\\Images\\1676376889173.jpg"
    },
    {
      "src": "C:\\Users\\User pc\\Pictures\\Images\\1676376889948.jpg",
      "dst": "C:\\Users\\User pc\\Pictures\\Images\\Images\\1676376889948.jpg"
    },
    {
      "src": "C:\\Users\\User pc\\Pictures\\Images\\1676376890755.jpg",
      "dst": "C:\\Users\\User pc\\Pictures\\Images\\Images\\1676376890755.jpg"
    },
    {
      "src": "C:\\Users\\User pc\\Pictures\\Images\\1676376891507.jpg",
      "dst": "C:\\Users\\User pc\\Pictures\\Images\\Images\\1676376891507.jpg"
    },
    {
      "src": "C:\\Users\\User pc\\Pictures\\Images\\1676376892396.jpg",
      "dst": "C:\\Users\\User pc\\Pictures\\Images\\Images\\1676376892396.jpg"
    },
    {
      "src": "C:\\Users\\User pc\\Pictures\\Images\\1676376894077.jpg",
      "dst": "C:\\Users\\User pc\\Pictures\\Images\\Images\\1676376894077.jpg"
    },
    {
      "src": "C:\\Users\\User pc\\Pictures\\Images\\1676376894889.jpg",
      "dst": "C:\\Users\\User pc\\Pictures\\Images\\Images\\1676376894889.jpg"
    },
    {
      "src": "C:\\Users\\User pc\\Pictures\\Images\\1676376895680.jpg",
      "dst": "C:\\Users\\User pc\\Pictures\\Images\\Images\\1676376895680.jpg"
    },
    {
      "src": "C:\\Users\\User pc\\Pictures\\Images\\1676376896516.jpg",
      "dst": "C:\\Users\\User pc\\Pictures\\Images\\Images\\1676376896516.jpg"
    },
    {
      "src": "C:\\Users\\User pc\\Pictures\\Images\\1676376897367.jpg",
      "dst": "C:\\Users\\User pc\\Pictures\\Images\\Images\\1676376897367.jpg"
    },
    {
      "src": "C:\\Users\\User pc\\Pictures\\Images\\1676376898215.jpg",
      "dst": "C:\\Users\\User pc\\Pictures\\Images\\Images\\1676376898215.jpg"
    },
    {
      "src": "C:\\Users\\User pc\\Pictures\\Images\\1676376899098.jpg",
      "dst": "C:\\Users\\User pc\\Pictures\\Images\\Images\\1676376899098.jpg"
    },
    {
      "src": "C:\\Users\\User pc\\Pictures\\Images\\1676376899834.jpg",
      "dst": "C:\\Users\\User pc\\Pictures\\Images\\Images\\1676376899834.jpg"
    },
    {
      "src": "C:\\Users\\User pc\\Pictures\\Images\\1676376900695.jpg",
      "dst": "C:\\Users\\User pc\\Pictures\\Images\\Images\\1676376900695.jpg"
    },
    {
      "src": "C:\\Users\\User pc\\Pictures\\Images\\1676376901554.jpg",
      "dst": "C:\\Users\\User pc\\Pictures\\Images\\Images\\1676376901554.jpg"
    },
    {
      "src": "C:\\Users\\User pc\\Pictures\\Images\\1676376902506.jpg",
      "dst": "C:\\Users\\User pc\\Pictures\\Images\\Images\\1676376902506.jpg"
    },
    {
      "src": "C:\\Users\\User pc\\Pictures\\Images\\1676376903548.jpg",
      "dst": "C:\\Users\\User pc\\Pictures\\Images\\Images\\1676376903548.jpg"
    },
    {
      "src": "C:\\Users\\User pc\\Pictures\\Images\\1676376904384.jpg",
      "dst": "C:\\Users\\User pc\\Pictures\\Images\\Images\\1676376904384.jpg"
    },
    {
      "src": "C:\\Users\\User pc\\Pictures\\Images\\1676376905126.jpg",
      "dst": "C:\\Users\\User pc\\Pictures\\Images\\Images\\1676376905126.jpg"
    },
    {
      "src": "C:\\Users\\User pc\\Pictures\\Images\\1676376905880.jpg",
      "dst": "C:\\Users\\User pc\\Pictures\\Images\\Images\\1676376905880.jpg"
    },
    {
      "src": "C:\\Users\\User pc\\Pictures\\Images\\1676376906723.jpg",
      "dst": "C:\\Users\\User pc\\Pictures\\Images\\Images\\1676376906723.jpg"
    },
    {
      "src": "C:\\Users\\User pc\\Pictures\\Images\\1676376907567.jpg",
      "dst": "C:\\Users\\User pc\\Pictures\\Images\\Images\\1676376907567.jpg"
    },
    {
      "src": "C:\\Users\\User pc\\Pictures\\Images\\1676376908436.jpg",
      "dst": "C:\\Users\\User pc\\Pictures\\Images\\Images\\1676376908436.jpg"
    },
    {
      "src": "C:\\Users\\User pc\\Pictures\\Images\\1676376909246.jpg",
      "dst": "C:\\Users\\User pc\\Pictures\\Images\\Images\\1676376909246.jpg"
    },
    {
      "src": "C:\\Users\\User pc\\Pictures\\Images\\1676376910052.jpg",
      "dst": "C:\\Users\\User pc\\Pictures\\Images\\Images\\1676376910052.jpg"
    },
    {
      "src": "C:\\Users\\User pc\\Pictures\\Images\\1676376910779.jpg",
      "dst": "C:\\Users\\User pc\\Pictures\\Images\\Images\\1676376910779.jpg"
    },
    {
      "src": "C:\\Users\\User pc\\Pictures\\Images\\1676376911677.jpg",
      "dst": "C:\\Users\\User pc\\Pictures\\Images\\Images\\1676376911677.jpg"
    },
    {
      "src": "C:\\Users\\User pc\\Pictures\\Images\\1676376912395.jpg",
      "dst": "C:\\Users\\User pc\\Pictures\\Images\\Images\\1676376912395.jpg"
    },
    {
      "src": "C:\\Users\\User pc\\Pictures\\Images\\1676376913862.jpg",
      "dst": "C:\\Users\\User pc\\Pictures\\Images\\Images\\1676376913862.jpg"
    },
    {
      "src": "C:\\Users\\User pc\\Pictures\\Images\\1676376914669.jpg",
      "dst": "C:\\Users\\User pc\\Pictures\\Images\\Images\\1676376914669.jpg"
    },
    {
      "src": "C:\\Users\\User pc\\Pictures\\Images\\1676376915392.jpg",
      "dst": "C:\\Users\\User pc\\Pictures\\Images\\Images\\1676376915392.jpg"
    },
    {
      "src": "C:\\Users\\User pc\\Pictures\\Images\\1676376916900.jpg",
      "dst": "C:\\Users\\User pc\\Pictures\\Images\\Images\\1676376916900.jpg"
    },
    {
      "src": "C:\\Users\\User pc\\Pictures\\Images\\1676376918386.jpg",
      "dst": "C:\\Users\\User pc\\Pictures\\Images\\Images\\1676376918386.jpg"
    },
    {
      "src": "C:\\Users\\User pc\\Pictures\\Images\\1676376919185.jpg",
      "dst": "C:\\Users\\User pc\\Pictures\\Images\\Images\\1676376919185.jpg"
    },
    {
      "src": "C:\\Users\\User pc\\Pictures\\Images\\1676376920728.jpg",
      "dst": "C:\\Users\\User pc\\Pictures\\Images\\Images\\1676376920728.jpg"
    },
    {
      "src": "C:\\Users\\User pc\\Pictures\\Images\\1676376922327.jpg",
      "dst": "C:\\Users\\User pc\\Pictures\\Images\\Images\\1676376922327.jpg"
    },
    {
      "src": "C:\\Users\\User pc\\Pictures\\Images\\1676376923217.jpg",
      "dst": "C:\\Users\\User pc\\Pictures\\Images\\Images\\1676376923217.jpg"
    },
    {
      "src": "C:\\Users\\User pc\\Pictures\\Images\\1676376923992.jpg",
      "dst": "C:\\Users\\User pc\\Pictures\\Images\\Images\\1676376923992.jpg"
    },
    {
      "src": "C:\\Users\\User pc\\Pictures\\Images\\1676376930894.jpg",
      "dst": "C:\\Users\\User pc\\Pictures\\Images\\Images\\1676376930894.jpg"
    },
    {
      "src": "C:\\Users\\User pc\\Pictures\\Images\\1676376936380.jpg",
      "dst": "C:\\Users\\User pc\\Pictures\\Images\\Images\\1676376936380.jpg"
    },
    {
      "src": "C:\\Users\\User pc\\Pictures\\Images\\1676376937200.jpg",
      "dst": "C:\\Users\\User pc\\Pictures\\Images\\Images\\1676376937200.jpg"
    },
    {
      "src": "C:\\Users\\User pc\\Pictures\\Images\\1676376939870.jpg",
      "dst": "C:\\Users\\User pc\\Pictures\\Images\\Images\\1676376939870.jpg"
    },
    {
      "src": "C:\\Users\\User pc\\Pictures\\Images\\1676376940673.jpg",
      "dst": "C:\\Users\\User pc\\Pictures\\Images\\Images\\1676376940673.jpg"
    },
    {
      "src": "C:\\Users\\User pc\\Pictures\\Images\\1676376941577.jpg",
      "dst": "C:\\Users\\User pc\\Pictures\\Images\\Images\\1676376941577.jpg"
    },
    {
      "src": "C:\\Users\\User pc\\Pictures\\Images\\1676376942418.jpg",
      "dst": "C:\\Users\\User pc\\Pictures\\Images\\Images\\1676376942418.jpg"
    },
    {
      "src": "C:\\Users\\User pc\\Pictures\\Images\\1676376943240.jpg",
      "dst": "C:\\Users\\User pc\\Pictures\\Images\\Images\\1676376943240.jpg"
    },
    {
      "src": "C:\\Users\\User pc\\Pictures\\Images\\1676376944069.jpg",
      "dst": "C:\\Users\\User pc\\Pictures\\Images\\Images\\1676376944069.jpg"
    },
    {
      "src": "C:\\Users\\User pc\\Pictures\\Images\\1676376944891.jpg",
      "dst": "C:\\Users\\User pc\\Pictures\\Images\\Images\\1676376944891.jpg"
    },
    {
      "src": "C:\\Users\\User pc\\Pictures\\Images\\1676376945805.jpg",
      "dst": "C:\\Users\\User pc\\Pictures\\Images\\Images\\1676376945805.jpg"
    },
    {
      "src": "C:\\Users\\User pc\\Pictures\\Images\\1676376947507.jpg",
      "dst": "C:\\Users\\User pc\\Pictures\\Images\\Images\\1676376947507.jpg"
    },
    {
      "src": "C:\\Users\\User pc\\Pictures\\Images\\1676376948330.jpg",
      "dst": "C:\\Users\\User pc\\Pictures\\Images\\Images\\1676376948330.jpg"
    },
    {
      "src": "C:\\Users\\User pc\\Pictures\\Images\\1676376949263.jpg",
      "dst": "C:\\Users\\User pc\\Pictures\\Images\\Images\\1676376949263.jpg"
    },
    {
      "src": "C:\\Users\\User pc\\Pictures\\Images\\IMG_3787.jpeg",
      "dst": "C:\\Users\\User pc\\Pictures\\Images\\Images\\IMG_3787.jpeg"
    },
    {
      "src": "C:\\Users\\User pc\\Pictures\\Images\\IMG_3788.jpeg",
      "dst": "C:\\Users\\User pc\\Pictures\\Images\\Images\\IMG_3788.jpeg"
    },
    {
      "src": "C:\\Users\\User pc\\Pictures\\Images\\IMG_3789.jpeg",
      "dst": "C:\\Users\\User pc\\Pictures\\Images\\Images\\IMG_3789.jpeg"
    },
    {
      "src": "C:\\Users\\User pc\\Pictures\\Images\\IMG_3792.jpeg",
      "dst": "C:\\Users\\User pc\\Pictures\\Images\\Images\\IMG_3792.jpeg"
    },
    {
      "src": "C:\\Users\\User pc\\Pictures\\Images\\IMG_3793.jpeg",
      "dst": "C:\\Users\\User pc\\Pictures\\Images\\Images\\IMG_3793.jpeg"
    },
    {
      "src": "C:\\Users\\User pc\\Pictures\\Images\\IMG_3798.jpeg",
      "dst": "C:\\Users\\User pc\\Pictures\\Images\\Images\\IMG_3798.jpeg"
    },
    {
      "src": "C:\\Users\\User pc\\Pictures\\Images\\IMG_3804.jpeg",
      "dst": "C:\\Users\\User pc\\Pictures\\Images\\Images\\IMG_3804.jpeg"
    },
    {
      "src": "C:\\Users\\User pc\\Pictures\\Images\\IMG_3805.jpeg",
      "dst": "C:\\Users\\User pc\\Pictures\\Images\\Images\\IMG_3805.jpeg"
    },
    {
      "src": "C:\\Users\\User pc\\Pictures\\Images\\IMG_3806.jpeg",
      "dst": "C:\\Users\\User pc\\Pictures\\Images\\Images\\IMG_3806.jpeg"
    },
    {
      "src": "C:\\Users\\User pc\\Pictures\\Images\\IMG_3808.jpeg",
      "dst": "C:\\Users\\User pc\\Pictures\\Images\\Images\\IMG_3808.jpeg"
    },
    {
      "src": "C:\\Users\\User pc\\Pictures\\Images\\IMG_3809.jpeg",
      "dst": "C:\\Users\\User pc\\Pictures\\Images\\Images\\IMG_3809.jpeg"
    },
    {
      "src": "C:\\Users\\User pc\\Pictures\\Images\\PXL_20230328_104545976.jpg",
      "dst": "C:\\Users\\User pc\\Pictures\\Images\\Images\\PXL_20230328_104545976.jpg"
    },
    {
      "src": "C:\\Users\\User pc\\Pictures\\Images\\PXL_20230328_104555829.jpg",
      "dst": "C:\\Users\\User pc\\Pictures\\Images\\Images\\PXL_20230328_104555829.jpg"
    },
    {
      "src": "C:\\Users\\User pc\\Pictures\\Images\\PXL_20230328_104621058.jpg",
      "dst": "C:\\Users\\User pc\\Pictures\\Images\\Images\\PXL_20230328_104621058.jpg"
    },
    {
      "src": "C:\\Users\\User pc\\Pictures\\Images\\PXL_20230328_104622710.jpg",
      "dst": "C:\\Users\\User pc\\Pictures\\Images\\Images\\PXL_20230328_104622710.jpg"
    },
    {
      "src": "C:\\Users\\User pc\\Pictures\\Images\\PXL_20230328_104701948.jpg",
      "dst": "C:\\Users\\User pc\\Pictures\\Images\\Images\\PXL_20230328_104701948.jpg"
    },
    {
      "src": "C:\\Users\\User pc\\Pictures\\Images\\PXL_20230328_104947238.jpg",
      "dst": "C:\\Users\\User pc\\Pictures\\Images\\Images\\PXL_20230328_104947238.jpg"
    },
    {
      "src": "C:\\Users\\User pc\\Pictures\\Images\\PXL_20230328_104951243.jpg",
      "dst": "C:\\Users\\User pc\\Pictures\\Images\\Images\\PXL_20230328_104951243.jpg"
    },
    {
      "src": "C:\\Users\\User pc\\Pictures\\Images\\PXL_20230328_105018513.jpg",
      "dst": "C:\\Users\\User pc\\Pictures\\Images\\Images\\PXL_20230328_105018513.jpg"
    },
    {
      "src": "C:\\Users\\User pc\\Pictures\\Images\\PXL_20230328_105048177.jpg",
      "dst": "C:\\Users\\User pc\\Pictures\\Images\\Images\\PXL_20230328_105048177.jpg"
    },
    {
      "src": "C:\\Users\\User pc\\Pictures\\Images\\PXL_20230328_105052698.jpg",
      "dst": "C:\\Users\\User pc\\Pictures\\Images\\Images\\PXL_20230328_105052698.jpg"
    },
    {
      "src": "C:\\Users\\User pc\\Pictures\\Images\\PXL_20230328_171358246.jpg",
      "dst": "C:\\Users\\User pc\\Pictures\\Images\\Images\\PXL_20230328_171358246.jpg"
    },
    {
      "src": "C:\\Users\\User pc\\Pictures\\Images\\PXL_20230328_171435229.jpg",
      "dst": "C:\\Users\\User pc\\Pictures\\Images\\Images\\PXL_20230328_171435229.jpg"
    },
    {
      "src": "C:\\Users\\User pc\\Pictures\\Images\\PXL_20230328_171437654.jpg",
      "dst": "C:\\Users\\User pc\\Pictures\\Images\\Images\\PXL_20230328_171437654.jpg"
    },
    {
      "src": "C:\\Users\\User pc\\Pictures\\Images\\PXL_20230328_171519468.jpg",
      "dst": "C:\\Users\\User pc\\Pictures\\Images\\Images\\PXL_20230328_171519468.jpg"
    },
    {
      "src": "C:\\Users\\User pc\\Pictures\\Images\\PXL_20230328_171519468~2.jpg",
      "dst": "C:\\Users\\User pc\\Pictures\\Images\\Images\\PXL_20230328_171519468~2.jpg"
    },
    {
      "src": "C:\\Users\\User pc\\Pictures\\Images\\PXL_20230328_171523990.jpg",
      "dst": "C:\\Users\\User pc\\Pictures\\Images\\Images\\PXL_20230328_171523990.jpg"
    },
    {
      "src": "C:\\Users\\User pc\\Pictures\\Images\\PXL_20230710_085852747.jpg",
      "dst": "C:\\Users\\User pc\\Pictures\\Images\\Images\\PXL_20230710_085852747.jpg"
    },
    {
      "src": "C:\\Users\\User pc\\Pictures\\Images\\PXL_20230710_085952734.jpg",
      "dst": "C:\\Users\\User pc\\Pictures\\Images\\Images\\PXL_20230710_085952734.jpg"
    },
    {
      "src": "C:\\Users\\User pc\\Pictures\\Images\\PXL_20230710_090005624.jpg",
      "dst": "C:\\Users\\User pc\\Pictures\\Images\\Images\\PXL_20230710_090005624.jpg"
    },
    {
      "src": "C:\\Users\\User pc\\Pictures\\Images\\PXL_20230710_090043253.jpg",
      "dst": "C:\\Users\\User pc\\Pictures\\Images\\Images\\PXL_20230710_090043253.jpg"
    },
    {
      "src": "C:\\Users\\User pc\\Pictures\\Images\\PXL_20230710_090048838.jpg",
      "dst": "C:\\Users\\User pc\\Pictures\\Images\\Images\\PXL_20230710_090048838.jpg"
    },
    {
      "src": "C:\\Users\\User pc\\Pictures\\Images\\PXL_20230804_162239877.jpg",
      "dst": "C:\\Users\\User pc\\Pictures\\Images\\Images\\PXL_20230804_162239877.jpg"
    },
    {
      "src": "C:\\Users\\User pc\\Pictures\\Images\\PXL_20230804_162426835.jpg",
      "dst": "C:\\Users\\User pc\\Pictures\\Images\\Images\\PXL_20230804_162426835.jpg"
    },
    {
      "src": "C:\\Users\\User pc\\Pictures\\Images\\PXL_20230804_162447170.jpg",
      "dst": "C:\\Users\\User pc\\Pictures\\Images\\Images\\PXL_20230804_162447170.jpg"
    },
    {
      "src": "C:\\Users\\User pc\\Pictures\\Images\\PXL_20230804_162507481.jpg",
      "dst": "C:\\Users\\User pc\\Pictures\\Images\\Images\\PXL_20230804_162507481.jpg"
    },
    {
      "src": "C:\\Users\\User pc\\Pictures\\Images\\PXL_20230804_162719618.jpg",
      "dst": "C:\\Users\\User pc\\Pictures\\Images\\Images\\PXL_20230804_162719618.jpg"
    },
    {
      "src": "C:\\Users\\User pc\\Pictures\\Images\\PXL_20230804_162726053.jpg",
      "dst": "C:\\Users\\User pc\\Pictures\\Images\\Images\\PXL_20230804_162726053.jpg"
    },
    {
      "src": "C:\\Users\\User pc\\Pictures\\Images\\PXL_20230804_162732696.jpg",
      "dst": "C:\\Users\\User pc\\Pictures\\Images\\Images\\PXL_20230804_162732696.jpg"
    },
    {
      "src": "C:\\Users\\User pc\\Pictures\\Images\\PXL_20230804_162737088.jpg",
      "dst": "C:\\Users\\User pc\\Pictures\\Images\\Images\\PXL_20230804_162737088.jpg"
    },
    {
      "src": "C:\\Users\\User pc\\Pictures\\Images\\PXL_20230805_123849246.jpg",
      "dst": "C:\\Users\\User pc\\Pictures\\Images\\Images\\PXL_20230805_123849246.jpg"
    },
    {
      "src": "C:\\Users\\User pc\\Pictures\\Images\\PXL_20230805_123911166.jpg",
      "dst": "C:\\Users\\User pc\\Pictures\\Images\\Images\\PXL_20230805_123911166.jpg"
    }
  ]
}